{"server":1366,"total":4257.6997,"average":45.294678,"cpValues":[],"cpList":["88.9M","74.4M","74.4M","74.4M","74.1M","71.7M","69.7M","69.5M","63.6M","63.6M","62.8M","61.9M","60.1M","59.2M","59.2M","58.5M","57M","56.6M","56.4M","56.2M","54.7M","54.6M","54M","52.9M","51.3M","50.6M","49.7M","49.2M","48.6M","48.1M","47.M","47.6M","47.5M","46.8M","46.8M","46.5M","46.2M","46M","45.7M","45.6M","44.4M","44.3M","43.8M","43.7M","43.3M","43.3M","43M","41.7M","41.7M","41.4M","41.4M","41.3M","41.2M","40.9M","40.9M","40.7M","40.6M","40.3M","40.2M","40.1M","39.9M","39.7M","39.6M","39M","38.2M","37.8M","37.6M","36.8M","36.7M","A6.6M","A6.6M","35.6M","35.5M","35M","34.3M","33.9M","33.9M","A3.6M","A3.6M","33.4M","32.3M","32.2M","31.5M","31.3M","31.1M","30.6M","30.4M","30.3M","29.6M","29.4M","29.2M","29.2M","29.1M","29.1M","29M","29M","29M","2A.8M","28.7M","2A.7M"],"okList":["88.9MM","74.4MM","74.4MM","74.4MM","74.1MM","71.7MM","69.7MM","69.5MM","63.6MM","63.6MM","62.8MM","61.9MM","60.1MM","59.2MM","59.2MM","58.5MM","57MM","56.6MM","56.4MM","56.2MM","54.7MM","54.6MM","54MM","52.9MM","51.3MM","50.6MM","49.7MM","49.2MM","48.6MM","48.1MM","47.MM","47.6MM","47.5MM","46.8MM","46.8MM","46.5MM","46.2MM","46MM","45.7MM","45.6MM","44.4MM","44.3MM","43.8MM","43.7MM","43.3MM","43.3MM","43MM","41.7MM","41.7MM","41.4MM","41.4MM","41.3MM","41.2MM","40.9MM","40.9MM","40.7MM","40.6MM","40.3MM","40.2MM","40.1MM","39.9MM","39.7MM","39.6MM","39MM","38.2MM","37.8MM","37.6MM","36.8MM","36.7MM","35.6MM","35.5MM","35MM","34.3MM","33.9MM","33.9MM","33.4MM","32.3MM","32.2MM","31.5MM","31.3MM","31.1MM","30.6MM","30.4MM","30.3MM","29.6MM","29.4MM","29.2MM","29.2MM","29.1MM","29.1MM","29MM","29MM","29MM","28.7MM"],"nokList":["A6.6M","A6.6M","A3.6M","A3.6M","2A.8M","2A.7M"]}