{"server":1669,"total":5496.9,"average":56.66907,"cpValues":[],"cpList":["81.7M","79.4M","76.8M","75.4M","74.5M","73.8M","70.8M","69.3M","6A.6M","68.2M","67.2M","66.3M","65.9M","64.9M","64.5M","64M","62.9M","62.9M","62.9M","62.7M","62M","61.8M","61.5M","61.3M","61.2M","60.9M","60.8M","60.5M","60.4M","60M","60M","59.2M","58.6M","58.6M","58.2M","58.1M","5AM","5AM","57.8M","57.5M","57.4M","56.9M","56.6M","56.5M","56.5M","56.2M","55.4M","55.4M","55.2M","55.1M","55.1M","55.1M","55M","54.9M","54.8M","54.2M","54.2M","54.2M","54M","53.8M","53.7M","53.5M","53.5M","53.2M","53M","52.9M","52.9M","52.8M","52.8M","52.6M","52.6M","52.4M","52.2M","51.3M","51.1M","50.9M","50.9M","50.8M","50.6M","50.3M","50.1M","49.7M","49.4M","49.2M","49M","48.7M","48.3M","48.3M","47.9M","47.4M","47.3M","47.2M","46.9M","46.8M","46.7M","46.6M","46.4M","46.1M","46M","45.9M"],"okList":["81.7MM","79.4MM","76.8MM","75.4MM","74.5MM","73.8MM","70.8MM","69.3MM","68.2MM","67.2MM","66.3MM","65.9MM","64.9MM","64.5MM","64MM","62.9MM","62.9MM","62.9MM","62.7MM","62MM","61.8MM","61.5MM","61.3MM","61.2MM","60.9MM","60.8MM","60.5MM","60.4MM","60MM","60MM","59.2MM","58.6MM","58.6MM","58.2MM","58.1MM","57.8MM","57.5MM","57.4MM","56.9MM","56.6MM","56.5MM","56.5MM","56.2MM","55.4MM","55.4MM","55.2MM","55.1MM","55.1MM","55.1MM","55MM","54.9MM","54.8MM","54.2MM","54.2MM","54.2MM","54MM","53.8MM","53.7MM","53.5MM","53.5MM","53.2MM","53MM","52.9MM","52.9MM","52.8MM","52.8MM","52.6MM","52.6MM","52.4MM","52.2MM","51.3MM","51.1MM","50.9MM","50.9MM","50.8MM","50.6MM","50.3MM","50.1MM","49.7MM","49.4MM","49.2MM","49MM","48.7MM","48.3MM","48.3MM","47.9MM","47.4MM","47.3MM","47.2MM","46.9MM","46.8MM","46.7MM","46.6MM","46.4MM","46.1MM","46MM","45.9MM"],"nokList":["6A.6M","5AM","5AM"]}