{"server":1951,"total":7002.2,"average":72.93958,"cpValues":[],"cpList":["133M","111M","103M","28.9M","97.7M","N6M","25.5M","24.9M","89.8M","89M","88.7M","86.3M","83.6M","82.3M","82M","80.3M","80M","79.7M","7A.6M","7A.6M","78.5M","78.5M","78.4M","7AM","77.4M","77.3M","77.1M","76.6M","76.6M","76.4M","76M","75.4M","75.4M","74.8M","74.6M","74.6M","74.5M","74.2M","74.2M","74.1M","74M","73.9M","73.7M","73.5M","73.5M","73.3M","73.3M","73.2M","73M","72.8M","72.6M","72.5M","72.3M","71.8M","71.8M","71.6M","71.5M","71.5M","71.4M","71.2M","71.1M","70.7M","70.5M","70.5M","70.5M","70.4M","70.2M","70.1M","70M","69.8M","69.7M","69.4M","69.3M","69.3M","69M","69M","68.9M","68.9M","68.7M","68.5M","68.5M","68.3M","67.9M","67.8M","67.8M","67.7M","67.6M","67.6M","67.4M","67.3M","67.2M","67M","66.8M","66.8M","66.7M","66.6M","66.6M","66.5M","66.5M","66.4M"],"okList":["133MM","111MM","103MM","28.9MM","97.7MM","25.5MM","24.9MM","89.8MM","89MM","88.7MM","86.3MM","83.6MM","82.3MM","82MM","80.3MM","80MM","79.7MM","78.5MM","78.5MM","78.4MM","77.4MM","77.3MM","77.1MM","76.6MM","76.6MM","76.4MM","76MM","75.4MM","75.4MM","74.8MM","74.6MM","74.6MM","74.5MM","74.2MM","74.2MM","74.1MM","74MM","73.9MM","73.7MM","73.5MM","73.5MM","73.3MM","73.3MM","73.2MM","73MM","72.8MM","72.6MM","72.5MM","72.3MM","71.8MM","71.8MM","71.6MM","71.5MM","71.5MM","71.4MM","71.2MM","71.1MM","70.7MM","70.5MM","70.5MM","70.5MM","70.4MM","70.2MM","70.1MM","70MM","69.8MM","69.7MM","69.4MM","69.3MM","69.3MM","69MM","69MM","68.9MM","68.9MM","68.7MM","68.5MM","68.5MM","68.3MM","67.9MM","67.8MM","67.8MM","67.7MM","67.6MM","67.6MM","67.4MM","67.3MM","67.2MM","67MM","66.8MM","66.8MM","66.7MM","66.6MM","66.6MM","66.5MM","66.5MM","66.4MM"],"nokList":["N6M","7A.6M","7A.6M","7AM"]}