{"server":2542,"total":2910.1,"average":29.39495,"cpValues":[],"cpList":["58.5M","53.9M","53.3M","53M","50.9M","50.4M","46.5M","46.2M","44.5M","43M","42.1M","41.4M","41.2M","40.8M","40.6M","37.9M","37.9M","35.9M","35.7M","35.2M","35.1M","34.9M","34.9M","34.8M","33.9M","33.5M","33.4M","32.3M","32.2M","32M","31.7M","30.9M","30.1M","30M","30M","29M","29.7M","29.7M","28.6M","28.4M","28.3M","28.1M","27.8M","27.8M","27.6M","27.1M","27M","26.8M","26.8M","26.7M","26.7M","26.5M","26.4M","26.4M","26M","25.7M","25.3M","25.3M","25.3M","25.2M","24.9M","24.9M","24.6M","24.4M","24.1M","24.1M","23.7M","23.7M","23.4M","23.4M","23.2M","23.1M","22.9M","22.8M","22.8M","22.3M","22.2M","21.8M","21.6M","21.4M","21.4M","21.2M","21.1M","21M","21M","20.8M","20.7M","20.6M","20.6M","20.6M","20.5M","20.3M","Z0.2M","20M","19.9M","19.9M","19.7M","19.7M","19.6M","19.4M"],"okList":["58.5MM","53.9MM","53.3MM","53MM","50.9MM","50.4MM","46.5MM","46.2MM","44.5MM","43MM","42.1MM","41.4MM","41.2MM","40.8MM","40.6MM","37.9MM","37.9MM","35.9MM","35.7MM","35.2MM","35.1MM","34.9MM","34.9MM","34.8MM","33.9MM","33.5MM","33.4MM","32.3MM","32.2MM","32MM","31.7MM","30.9MM","30.1MM","30MM","30MM","29MM","29.7MM","29.7MM","28.6MM","28.4MM","28.3MM","28.1MM","27.8MM","27.8MM","27.6MM","27.1MM","27MM","26.8MM","26.8MM","26.7MM","26.7MM","26.5MM","26.4MM","26.4MM","26MM","25.7MM","25.3MM","25.3MM","25.3MM","25.2MM","24.9MM","24.9MM","24.6MM","24.4MM","24.1MM","24.1MM","23.7MM","23.7MM","23.4MM","23.4MM","23.2MM","23.1MM","22.9MM","22.8MM","22.8MM","22.3MM","22.2MM","21.8MM","21.6MM","21.4MM","21.4MM","21.2MM","21.1MM","21MM","21MM","20.8MM","20.7MM","20.6MM","20.6MM","20.6MM","20.5MM","20.3MM","20MM","19.9MM","19.9MM","19.7MM","19.7MM","19.6MM","19.4MM"],"nokList":["Z0.2M"]}