{"server":2693,"total":6041.1,"average":62.27938,"cpValues":[],"cpList":["85.5M","84.6M","82.8M","82.1M","80.3M","80.2M","77M","76.9M","74.1M","71.9M","71.8M","70.9M","69.9M","69.8M","69.6M","6A.6M","68.5M","67.8M","67.2M","67.2M","67.1M","66.9M","66.6M","66.3M","65.8M","65.6M","65M","65M","64.9M","64.7M","64.4M","64.2M","64.1M","64M","63.7M","62.9M","62.7M","62.6M","62.3M","61.9M","61.8M","61.8M","61.4M","61.4M","61M","60.8M","60.8M","59.9M","59.8M","59.8M","59.6M","59.5M","59.4M","59M","58.9M","58.7M","58.7M","58.6M","58.3M","58.3M","58.2M","5AM","57.QM","57.6M","57.6M","57.5M","57.3M","57.1M","57.1M","57M","57M","56.9M","56.8M","56.8M","56.8M","56.8M","56.7M","56.7M","56.7M","56.5M","56.3M","56.3M","56.1M","56.1M","56M","55.9M","55.9M","55.7M","55.5M","55.4M","55.4M","55.1M","55.1M","55M","54.8M","54.7M","54.7M","54.6M","54.6M","54.5M"],"okList":["85.5MM","84.6MM","82.8MM","82.1MM","80.3MM","80.2MM","77MM","76.9MM","74.1MM","71.9MM","71.8MM","70.9MM","69.9MM","69.8MM","69.6MM","68.5MM","67.8MM","67.2MM","67.2MM","67.1MM","66.9MM","66.6MM","66.3MM","65.8MM","65.6MM","65MM","65MM","64.9MM","64.7MM","64.4MM","64.2MM","64.1MM","64MM","63.7MM","62.9MM","62.7MM","62.6MM","62.3MM","61.9MM","61.8MM","61.8MM","61.4MM","61.4MM","61MM","60.8MM","60.8MM","59.9MM","59.8MM","59.8MM","59.6MM","59.5MM","59.4MM","59MM","58.9MM","58.7MM","58.7MM","58.6MM","58.3MM","58.3MM","58.2MM","57.6MM","57.6MM","57.5MM","57.3MM","57.1MM","57.1MM","57MM","57MM","56.9MM","56.8MM","56.8MM","56.8MM","56.8MM","56.7MM","56.7MM","56.7MM","56.5MM","56.3MM","56.3MM","56.1MM","56.1MM","56MM","55.9MM","55.9MM","55.7MM","55.5MM","55.4MM","55.4MM","55.1MM","55.1MM","55MM","54.8MM","54.7MM","54.7MM","54.6MM","54.6MM","54.5MM"],"nokList":["6A.6M","5AM","57.QM"]}